fastrts.py
fastrts-1.0.7.dist-info/METADATA
fastrts-1.0.7.dist-info/WHEEL
fastrts-1.0.7.dist-info/top_level.txt
fastrts-1.0.7.dist-info/RECORD
