Metadata-Version: 2.1
Name: fastrts
Version: 1.0.7
Summary: FastRTS has been renamed BabelRTS. Check it out here: https://github.com/GabrieleMaurina/babelRTS. Install it with "python -m pip install babelrts".
Home-page: https://github.com/GabrieleMaurina/babelRTS
Author: Gabriele Maurina
Author-email: gabrielemaurina95@gmail.com
License: MIT
Platform: UNKNOWN
Classifier: Programming Language :: Python :: 3
Classifier: License :: OSI Approved :: MIT License
Classifier: Operating System :: OS Independent
Requires-Python: >=3.8
Requires-Dist: dext
